sylte/__init__.py
sylte/_sylte.py
sylte-0.0.3.dist-info/LICENSE
sylte-0.0.3.dist-info/WHEEL
sylte-0.0.3.dist-info/METADATA
sylte-0.0.3.dist-info/RECORD
