Metadata-Version: 2.1
Name: sylte
Version: 0.0.3
Summary: Pickling and unpickling of function arguments
Home-page: https://github.com/danhje/sylte
License: MIT
Keywords: pickle,pickling,arguments,debug,cache
Author: Daniel Hjertholm
Author-email: daniel.hjertholm@icloud.com
Requires-Python: >=3.8,<4.0
Classifier: Development Status :: 4 - Beta
Classifier: Intended Audience :: Developers
Classifier: License :: OSI Approved :: MIT License
Classifier: Natural Language :: English
Classifier: Operating System :: OS Independent
Classifier: Programming Language :: Python :: 3
Classifier: Programming Language :: Python :: 3.10
Classifier: Programming Language :: Python :: 3.8
Classifier: Programming Language :: Python :: 3.9
Classifier: Topic :: Software Development :: Libraries
Classifier: Topic :: Software Development :: Libraries :: Python Modules
Requires-Dist: appdirs
Project-URL: Repository, https://github.com/danhje/sylte
